wavesync/__init__.py
wavesync/wavesync.py
PyWaveSync-0.1.1.dist-info/LICENSE
PyWaveSync-0.1.1.dist-info/METADATA
PyWaveSync-0.1.1.dist-info/WHEEL
PyWaveSync-0.1.1.dist-info/top_level.txt
PyWaveSync-0.1.1.dist-info/RECORD
