Metadata-Version: 2.1
Name: PyWaveSync
Version: 0.1.1
Summary: WaveSync is a Python library for nuanced, nonlinear, and rapid analysis of vectors and embeddings, tailored for RAG systems.
Home-page: https://github.com/guyfloki/wavesync
Author: Liubomyr Horbatko
Author-email: liubomir.horbatko@gmail.com
Classifier: Programming Language :: Python :: 3
Classifier: License :: OSI Approved :: MIT License
Classifier: Operating System :: OS Independent
License-File: LICENSE
Requires-Dist: numpy
Requires-Dist: PyWavelets
